symbol_convert/__init__.py
symbol_convert/__version__.py
symbol_convert/_convert.py
symbol_convert-0.1.dist-info/METADATA
symbol_convert-0.1.dist-info/WHEEL
symbol_convert-0.1.dist-info/licenses/LICENSE
symbol_convert-0.1.dist-info/RECORD
